{
    "parent": "apotheosis:gateways/frontier",
    "criteria": {
        "impossible": {
            "trigger": "minecraft:impossible"
        }
    },
    "display": {
        "background": "apotheosis:textures/advancements/bg/apoth.png",
        "description": {
            "translate": "advancements.apotheosis.progression.ascent.desc"
        },
        "frame": "goal",
        "icon": {
            "count": 1,
            "id": "minecraft:blaze_powder"
        },
        "title": {
            "translate": "advancements.apotheosis.progression.ascent.title"
        }
    },
    "requirements": [
        [
            "impossible"
        ]
    ],
    "sends_telemetry_event": true
}